baihu_logging/__init__.py
baihu_logging/client.py
baihu_logging/constants.py
baihu_logging-1.1.2.dist-info/licenses/LICENSE
baihu_logging-1.1.2.dist-info/METADATA
baihu_logging-1.1.2.dist-info/WHEEL
baihu_logging-1.1.2.dist-info/top_level.txt
baihu_logging-1.1.2.dist-info/RECORD
