Metadata-Version: 2.4
Name: baihu-logging
Version: 1.1.2
Summary: A logging bot which can log messages to Discord
Home-page: https://github.com/baihufox3210/Baihu-Logging
Author: Baihu
Author-email: baihu3210@gmail.com
Classifier: Programming Language :: Python :: 3
Classifier: License :: OSI Approved :: MIT License
Classifier: Operating System :: OS Independent
Requires-Python: >=3.6
License-File: LICENSE
Requires-Dist: requests
Requires-Dist: colorama
Dynamic: author
Dynamic: author-email
Dynamic: classifier
Dynamic: description
Dynamic: description-content-type
Dynamic: home-page
Dynamic: license-file
Dynamic: requires-dist
Dynamic: requires-python
Dynamic: summary
